odoo9_addon_help_online-9.0.1.0.0-py2.7-nspkg.pth
odoo_addons/help_online/__openerp__.py
odoo_addons/help_online/__init__.py
odoo_addons/help_online/README.rst
odoo_addons/help_online/security/help_online_groups.xml
odoo_addons/help_online/security/help_online_rules.xml
odoo_addons/help_online/models/__init__.py
odoo_addons/help_online/models/ir_model.py
odoo_addons/help_online/models/help_online.py
odoo_addons/help_online/i18n/help_online.pot
odoo_addons/help_online/i18n/sl.po
odoo_addons/help_online/i18n/fr.po
odoo_addons/help_online/views/help_online_view.xml
odoo_addons/help_online/views/ir_ui_view_view.xml
odoo_addons/help_online/controllers/__init__.py
odoo_addons/help_online/controllers/help_online_controllers.py
odoo_addons/help_online/wizards/export_help_wizard_view.xml
odoo_addons/help_online/wizards/import_help_wizard_view.xml
odoo_addons/help_online/wizards/export_help_wizard.py
odoo_addons/help_online/wizards/__init__.py
odoo_addons/help_online/wizards/import_help_wizard.py
odoo_addons/help_online/data/ir_config_parameter_data.xml
odoo_addons/help_online/data/help_auto_backup.sample
odoo_addons/help_online/tests/test_import_help_wizard.py
odoo_addons/help_online/tests/test_help_online.py
odoo_addons/help_online/tests/__init__.py
odoo_addons/help_online/tests/test_export_help_wizard.py
odoo_addons/help_online/tests/common.py
odoo_addons/help_online/tests/data/help_test_data.xml
odoo_addons/help_online/static/description/help_online_create_page.png
odoo_addons/help_online/static/description/index.html
odoo_addons/help_online/static/description/help_online_view_page.png
odoo_addons/help_online/static/description/icon.png
odoo_addons/help_online/static/src/img/snippet/snippet_thumbs.png
odoo_addons/help_online/static/src/js/help_online.js
odoo_addons/help_online/static/src/css/help_online.css
odoo_addons/help_online/static/src/xml/help_online.xml
odoo9_addon_help_online-9.0.1.0.0.dist-info/top_level.txt
odoo9_addon_help_online-9.0.1.0.0.dist-info/WHEEL
odoo9_addon_help_online-9.0.1.0.0.dist-info/RECORD
odoo9_addon_help_online-9.0.1.0.0.dist-info/metadata.json
odoo9_addon_help_online-9.0.1.0.0.dist-info/DESCRIPTION.rst
odoo9_addon_help_online-9.0.1.0.0.dist-info/METADATA
odoo9_addon_help_online-9.0.1.0.0.dist-info/namespace_packages.txt
